idfops/__init__.py
idfops/pandas_filtering.py
idfops/pandas_operations.py
pandas_operations/__init__.py
pandas_operations/pandas_filtering.py
pandas_operations/pandas_operations.py
idfops-0.1.5.dist-info/LICENSE
idfops-0.1.5.dist-info/METADATA
idfops-0.1.5.dist-info/WHEEL
idfops-0.1.5.dist-info/top_level.txt
idfops-0.1.5.dist-info/RECORD
